colloid_polymer_phase_diagram/__init__.py
colloid_polymer_phase_diagram/phase.py
colloid_polymer_phase_diagram-0.3.1.dist-info/LICENSE.txt
colloid_polymer_phase_diagram-0.3.1.dist-info/METADATA
colloid_polymer_phase_diagram-0.3.1.dist-info/WHEEL
colloid_polymer_phase_diagram-0.3.1.dist-info/top_level.txt
colloid_polymer_phase_diagram-0.3.1.dist-info/RECORD
