Metadata-Version: 2.1
Name: colloid-polymer-phase-diagram
Version: 0.3.1
Summary: A Python module to compute the phase behaviour of Colloid+Polymer mixture
Home-page: https://github.com/MathieuLeocmach/colloid-polymer-phase-diagram
Author: Mathieu Leocmach
Author-email: mathieu.leocmach@univ-lyon1.fr
License: UNKNOWN
Platform: UNKNOWN
Requires-Python: >=2.5
Requires-Dist: numpy
Requires-Dist: scipy
